preloop/__init__.py
preloop/config.py
preloop/flow_presets.py
preloop/logging.py
preloop/server.py
preloop/agents/__init__.py
preloop/agents/aider.py
preloop/agents/base.py
preloop/agents/claude_code.py
preloop/agents/codex.py
preloop/agents/container.py
preloop/agents/factory.py
preloop/agents/gemini.py
preloop/agents/openhands.py
preloop/api/__init__.py
preloop/api/app.py
preloop/api/common.py
preloop/api/ssr.py
preloop/api/auth/__init__.py
preloop/api/auth/jwt.py
preloop/api/auth/permissions.py
preloop/api/auth/router.py
preloop/api/endpoints/__init__.py
preloop/api/endpoints/account.py
preloop/api/endpoints/ai_models.py
preloop/api/endpoints/approval_requests.py
preloop/api/endpoints/comments.py
preloop/api/endpoints/embedding.py
preloop/api/endpoints/features.py
preloop/api/endpoints/flows.py
preloop/api/endpoints/health.py
preloop/api/endpoints/impersonation.py
preloop/api/endpoints/issue_compliance.py
preloop/api/endpoints/issue_dependencies.py
preloop/api/endpoints/issue_duplicates.py
preloop/api/endpoints/issues.py
preloop/api/endpoints/mcp.py
preloop/api/endpoints/mcp_servers.py
preloop/api/endpoints/notification_preferences.py
preloop/api/endpoints/organizations.py
preloop/api/endpoints/projects.py
preloop/api/endpoints/public_approval.py
preloop/api/endpoints/roles.py
preloop/api/endpoints/search.py
preloop/api/endpoints/tools.py
preloop/api/endpoints/trackers.py
preloop/api/endpoints/version.py
preloop/api/endpoints/webhooks.py
preloop/api/endpoints/websockets.py
preloop/api/middleware/__init__.py
preloop/api/middleware/websocket_auth.py
preloop/models/__init__.py
preloop/models/py.typed
preloop/models/sentry.py
preloop/models/alembic/env.py
preloop/models/alembic/versions/20251105_initial_schema.py
preloop/models/alembic/versions/20251110_add_team_ids_to_user_invitation.py
preloop/models/alembic/versions/20251111_increase_issue_description_limit_to_text.py
preloop/models/alembic/versions/20251116_add_registration_token_table.py
preloop-0.8.0.dist-info/licenses/LICENSE
preloop-0.8.0.dist-info/METADATA
preloop-0.8.0.dist-info/WHEEL
preloop-0.8.0.dist-info/entry_points.txt
preloop-0.8.0.dist-info/top_level.txt
preloop-0.8.0.dist-info/RECORD
